pybuilder_anybadge/__init__.py
pybuilder_anybadge/task.py
pybuilder_anybadge-0.3.4.dist-info/METADATA
pybuilder_anybadge-0.3.4.dist-info/WHEEL
pybuilder_anybadge-0.3.4.dist-info/namespace_packages.txt
pybuilder_anybadge-0.3.4.dist-info/top_level.txt
pybuilder_anybadge-0.3.4.dist-info/zip-safe
pybuilder_anybadge-0.3.4.dist-info/RECORD
