Metadata-Version: 2.1
Name: pybuilder-anybadge
Version: 0.3.4
Summary: A pybuilder plugin that generates badges for your project
Home-page: https://github.com/soda480/pybuilder-anybadge
Author: Emilio Reyes
Author-email: soda480@gmail.com
Maintainer: 
Maintainer-email: 
License: Apache License, Version 2.0
Classifier: Programming Language :: Python
Classifier: Programming Language :: Python :: 3.7
Classifier: Programming Language :: Python :: 3.8
Classifier: Programming Language :: Python :: 3.9
Classifier: Programming Language :: Python :: 3.10
Classifier: Topic :: Software Development :: Build Tools
Requires-Dist: anybadge
